stanpy/__init__.py
stanpy/cross_section.py
stanpy/helpers.py
stanpy/plotting.py
stanpy/reduction.py
stanpy/test.py
stanpy/transfer_relation.py
stanpy/utils.py
stanpy/static/__init__.py
stanpy-0.2.11.dist-info/AUTHORS.rst
stanpy-0.2.11.dist-info/LICENSE
stanpy-0.2.11.dist-info/METADATA
stanpy-0.2.11.dist-info/WHEEL
stanpy-0.2.11.dist-info/top_level.txt
stanpy-0.2.11.dist-info/RECORD
