Metadata-Version: 2.1
Name: stanpy
Version: 0.2.11
Summary: Small python package for structural analysis
Home-page: https://stanpy-dev.david-zhou.org/
Author: David Zhou
Author-email: d.zhou@posteo.at
License: UNKNOWN
Project-URL: Bug Tracker, https://github.com/DavidNaizheZhou/stanpy/issues
Platform: UNKNOWN
Classifier: Programming Language :: Python :: 3
Classifier: License :: OSI Approved :: MIT License
Classifier: Operating System :: OS Independent
Requires-Python: >=3.6
License-File: LICENSE
License-File: AUTHORS.rst
